setup.py
My_binomial_distributions/Binomialdistribution.py
My_binomial_distributions/Gaussiandistribution.py
My_binomial_distributions/Generaldistribution.py
My_binomial_distributions/__init__.py
My_binomial_distributions.egg-info/PKG-INFO
My_binomial_distributions.egg-info/SOURCES.txt
My_binomial_distributions.egg-info/dependency_links.txt
My_binomial_distributions.egg-info/not-zip-safe
My_binomial_distributions.egg-info/top_level.txt